{"space_templates":[{"space_template_sid":"grassy-knoll-7748","selectable_by_non_admins":false,"graph_organization_id":null,"activity_name":"Grassy Knoll","selectable_for_experiences":false,"description":"","desktop_capacity":null,"mobile_capacity":null,"disabled_for_public_activities":false,"admin":false,"created_at":"2021-05-04T08:05:17.712-07:00","updated_at":"2021-05-04T08:55:07.011-07:00","tutorial":null,"is_featured":null,"space_template_id":"1729845549026247560","recording_id":"","asset_bundle_scenes":[{"aasm_state":"active","name":"Autogenerated for SpaceTemplate 1729845549026247560","created_at":"2021-05-04T08:05:17.771-07:00","updated_at":"2021-05-04T08:55:07.009-07:00","asset_bundle_scene_id":"1729845549286294411","user_id":"1610370333934617056","asset_bundles":[{"game_engine":"unity","game_engine_version":20194,"platform":"android","url":"https://cdn-content-ingress.altvr.com/environments/f0/89/f089673f30858fcb95be6a19ea6028f2-template-android","description":null,"color_space":null,"aasm_state":"active","created_at":"2021-05-04T08:55:06.905-07:00","updated_at":"2021-05-04T08:55:06.905-07:00","layout":null,"crc":"1266749928","client_cache_key":"f089673f30858fcb95be6a19ea6028f2","name":"template","stereo_render_mode":null,"uncompressed":null,"asset_bundle_id":"1729870624060342778","user_id":"1610370333934617056","asset_bundle_scene_id":"1729845549286294411","avatar_id":""},{"game_engine":"unity","game_engine_version":20194,"platform":"pc","url":"https://cdn-content-ingress.altvr.com/environments/f0/89/f089673f30858fcb95be6a19ea6028f2-template-pc","description":null,"color_space":null,"aasm_state":"active","created_at":"2021-05-04T08:55:06.732-07:00","updated_at":"2021-05-04T08:55:06.732-07:00","layout":null,"crc":"539951980","client_cache_key":"f089673f30858fcb95be6a19ea6028f2","name":"template","stereo_render_mode":null,"uncompressed":null,"asset_bundle_id":"1729870622617502200","user_id":"1610370333934617056","asset_bundle_scene_id":"1729845549286294411","avatar_id":""}]}],"image_large":"https://cdn-content-ingress.altvr.com/defaults/default-560x315.jpg","image_medium":"https://cdn-content-ingress.altvr.com/defaults/default-560x315.jpg","image_small":"https://cdn-content-ingress.altvr.com/defaults/default-560x315.jpg","image_thumbnail":"https://cdn-content-ingress.altvr.com/defaults/default-560x315.jpg","banner_image_large":"https://cdn-content-ingress.altvr.com/defaults/default-1920x576.jpg","banner_image_medium":"https://cdn-content-ingress.altvr.com/defaults/default-1920x576.jpg","banner_image_small":"https://cdn-content-ingress.altvr.com/defaults/default-1920x576.jpg","name":"Grassy Knoll"},{"space_template_sid":"nighty-night-1195","selectable_by_non_admins":false,"graph_organization_id":null,"activity_name":"Nighty Night (0.2 MB)","selectable_for_experiences":false,"description":"Basic flat templated with a starry skybox by default. 0.2 MB","desktop_capacity":null,"mobile_capacity":null,"disabled_for_public_activities":false,"admin":false,"created_at":"2021-04-23T10:09:25.462-07:00","updated_at":"2021-04-23T10:15:48.095-07:00","tutorial":null,"is_featured":null,"space_template_id":"1721935492246667284","recording_id":"","asset_bundle_scenes":[{"aasm_state":"active","name":"Autogenerated for SpaceTemplate 1721935492246667284","created_at":"2021-04-23T10:09:25.513-07:00","updated_at":"2021-04-23T10:10:05.241-07:00","asset_bundle_scene_id":"1721935492506714136","user_id":"1642792417906131497","asset_bundles":[{"game_engine":"unity","game_engine_version":20194,"platform":"android","url":"https://cdn-content-ingress.altvr.com/environments/88/46/88466f82625de70001e6f312c7bd9779-nightynight-android-android","description":null,"color_space":null,"aasm_state":"active","created_at":"2021-04-23T10:09:43.342-07:00","updated_at":"2021-04-23T10:09:43.342-07:00","layout":null,"crc":"1953073017","client_cache_key":"88466f82625de70001e6f312c7bd9779","name":"nightynight-android","stereo_render_mode":null,"uncompressed":null,"asset_bundle_id":"1721935642075594855","user_id":"1642792417906131497","asset_bundle_scene_id":"1721935492506714136","avatar_id":""},{"game_engine":"unity","game_engine_version":20194,"platform":"pc","url":"https://cdn-content-ingress.altvr.com/environments/e0/02/e00236ed54ccd4f001c45486d1b0c3ae-nightynight-windows-pc","description":null,"color_space":null,"aasm_state":"active","created_at":"2021-04-23T10:10:05.203-07:00","updated_at":"2021-04-23T10:10:05.203-07:00","layout":null,"crc":"1640520407","client_cache_key":"e00236ed54ccd4f001c45486d1b0c3ae","name":"nightynight-windows","stereo_render_mode":null,"uncompressed":null,"asset_bundle_id":"1721935825458954386","user_id":"1642792417906131497","asset_bundle_scene_id":"1721935492506714136","avatar_id":""}]}],"image_large":"https://cdn-content-ingress.altvr.com/uploads/space_template/image/1721935492246667284/0c4a6a97aff202505bc261525db75275.jpg","image_medium":"https://cdn-content-ingress.altvr.com/uploads/space_template/image/1721935492246667284/tile_0c4a6a97aff202505bc261525db75275.jpg","image_small":"https://cdn-content-ingress.altvr.com/uploads/space_template/image/1721935492246667284/tile_0c4a6a97aff202505bc261525db75275.jpg","image_thumbnail":"https://cdn-content-ingress.altvr.com/uploads/space_template/image/1721935492246667284/thumbnail_0c4a6a97aff202505bc261525db75275.jpg","banner_image_large":"https://cdn-content-ingress.altvr.com/defaults/default-1920x576.jpg","banner_image_medium":"https://cdn-content-ingress.altvr.com/defaults/default-1920x576.jpg","banner_image_small":"https://cdn-content-ingress.altvr.com/defaults/default-1920x576.jpg","name":"Nighty Night (0.2 MB)"},{"space_template_sid":"steps-world-test-7760","selectable_by_non_admins":false,"graph_organization_id":null,"activity_name":"Steps world Test","selectable_for_experiences":false,"description":"Experimenting like crazy, learning to build in Unity","desktop_capacity":null,"mobile_capacity":null,"disabled_for_public_activities":false,"admin":false,"created_at":"2021-04-26T00:48:58.451-07:00","updated_at":"2021-04-26T01:53:06.160-07:00","tutorial":null,"is_featured":null,"space_template_id":"1723827735568056620","recording_id":"","asset_bundle_scenes":[{"aasm_state":"active","name":"Autogenerated for SpaceTemplate 1723827735568056620","created_at":"2021-04-26T00:48:58.499-07:00","updated_at":"2021-04-26T01:53:06.158-07:00","asset_bundle_scene_id":"1723827735828103471","user_id":"1610370333934617056","asset_bundles":[{"game_engine":"unity","game_engine_version":20194,"platform":"android","url":"https://cdn-content-ingress.altvr.com/environments/87/f1/87f154c54bcd11ffeb685ffeca7011d1-template-android","description":null,"color_space":null,"aasm_state":"active","created_at":"2021-04-26T01:53:06.114-07:00","updated_at":"2021-04-26T01:53:06.114-07:00","layout":null,"crc":"3123024504","client_cache_key":"87f154c54bcd11ffeb685ffeca7011d1","name":"template","stereo_render_mode":null,"uncompressed":null,"asset_bundle_id":"1723860011928518918","user_id":"1610370333934617056","asset_bundle_scene_id":"1723827735828103471","avatar_id":""},{"game_engine":"unity","game_engine_version":20194,"platform":"pc","url":"https://cdn-content-ingress.altvr.com/environments/87/f1/87f154c54bcd11ffeb685ffeca7011d1-template-pc","description":null,"color_space":null,"aasm_state":"active","created_at":"2021-04-26T01:53:05.970-07:00","updated_at":"2021-04-26T01:53:05.970-07:00","layout":null,"crc":"235702763","client_cache_key":"87f154c54bcd11ffeb685ffeca7011d1","name":"template","stereo_render_mode":null,"uncompressed":null,"asset_bundle_id":"1723860010745725188","user_id":"1610370333934617056","asset_bundle_scene_id":"1723827735828103471","avatar_id":""}]}],"image_large":"https://cdn-content-ingress.altvr.com/defaults/default-560x315.jpg","image_medium":"https://cdn-content-ingress.altvr.com/defaults/default-560x315.jpg","image_small":"https://cdn-content-ingress.altvr.com/defaults/default-560x315.jpg","image_thumbnail":"https://cdn-content-ingress.altvr.com/defaults/default-560x315.jpg","banner_image_large":"https://cdn-content-ingress.altvr.com/defaults/default-1920x576.jpg","banner_image_medium":"https://cdn-content-ingress.altvr.com/defaults/default-1920x576.jpg","banner_image_small":"https://cdn-content-ingress.altvr.com/defaults/default-1920x576.jpg","name":"Steps world Test"},{"space_template_sid":"wip---sutro-heights-4631","selectable_by_non_admins":false,"graph_organization_id":null,"activity_name":"Sutro Heights","selectable_for_experiences":false,"description":"","desktop_capacity":null,"mobile_capacity":null,"disabled_for_public_activities":false,"admin":false,"created_at":"2021-05-01T07:47:36.114-07:00","updated_at":"2021-05-24T00:13:33.484-07:00","tutorial":null,"is_featured":null,"space_template_id":"1727662316461229049","recording_id":"","asset_bundle_scenes":[{"aasm_state":"active","name":"Autogenerated for SpaceTemplate 1727662316461229049","created_at":"2021-05-01T07:47:36.162-07:00","updated_at":"2021-05-24T00:13:33.483-07:00","asset_bundle_scene_id":"1727662316721275900","user_id":"1610370333934617056","asset_bundles":[{"game_engine":"unity","game_engine_version":20194,"platform":"android","url":"https://cdn-content-ingress.altvr.com/environments/e2/3a/e23acc907bed3b123f10022817d16129-template-android","description":null,"color_space":null,"aasm_state":"active","created_at":"2021-05-24T00:13:33.405-07:00","updated_at":"2021-05-24T00:13:33.405-07:00","layout":null,"crc":"436985532","client_cache_key":"e23acc907bed3b123f10022817d16129","name":"template","stereo_render_mode":null,"uncompressed":null,"asset_bundle_id":"1744103629771505859","user_id":"1610370333934617056","asset_bundle_scene_id":"1727662316721275900","avatar_id":""},{"game_engine":"unity","game_engine_version":20194,"platform":"pc","url":"https://cdn-content-ingress.altvr.com/environments/e2/3a/e23acc907bed3b123f10022817d16129-template-pc","description":null,"color_space":null,"aasm_state":"active","created_at":"2021-05-24T00:13:33.121-07:00","updated_at":"2021-05-24T00:13:33.121-07:00","layout":null,"crc":"3973744649","client_cache_key":"e23acc907bed3b123f10022817d16129","name":"template","stereo_render_mode":null,"uncompressed":null,"asset_bundle_id":"1744103627405918400","user_id":"1610370333934617056","asset_bundle_scene_id":"1727662316721275900","avatar_id":""}]}],"image_large":"https://cdn-content-ingress.altvr.com/defaults/default-560x315.jpg","image_medium":"https://cdn-content-ingress.altvr.com/defaults/default-560x315.jpg","image_small":"https://cdn-content-ingress.altvr.com/defaults/default-560x315.jpg","image_thumbnail":"https://cdn-content-ingress.altvr.com/defaults/default-560x315.jpg","banner_image_large":"https://cdn-content-ingress.altvr.com/defaults/default-1920x576.jpg","banner_image_medium":"https://cdn-content-ingress.altvr.com/defaults/default-1920x576.jpg","banner_image_small":"https://cdn-content-ingress.altvr.com/defaults/default-1920x576.jpg","name":"Sutro Heights"},{"space_template_sid":"the-cyber-outpost-3020","selectable_by_non_admins":false,"graph_organization_id":null,"activity_name":"The Cyber Outpost","selectable_for_experiences":false,"description":"AussieGuy92.com for more content.","desktop_capacity":null,"mobile_capacity":null,"disabled_for_public_activities":false,"admin":false,"created_at":"2021-04-26T04:36:10.288-07:00","updated_at":"2021-04-26T06:07:43.920-07:00","tutorial":null,"is_featured":null,"space_template_id":"1723942087688192410","recording_id":"","asset_bundle_scenes":[{"aasm_state":"active","name":"Autogenerated for SpaceTemplate 1723942087688192410","created_at":"2021-04-26T04:36:10.344-07:00","updated_at":"2021-04-26T06:07:43.915-07:00","asset_bundle_scene_id":"1723942088082456989","user_id":"1642792417906131497","asset_bundles":[{"game_engine":"unity","game_engine_version":20194,"platform":"android","url":"https://cdn-content-ingress.altvr.com/environments/7c/fd/7cfd532d25a87323c8fb5926f54908d7-template-android","description":null,"color_space":null,"aasm_state":"active","created_at":"2021-04-26T06:07:43.824-07:00","updated_at":"2021-04-26T06:07:43.824-07:00","layout":null,"crc":"286518836","client_cache_key":"7cfd532d25a87323c8fb5926f54908d7","name":"template","stereo_render_mode":null,"uncompressed":null,"asset_bundle_id":"1723988170682401651","user_id":"1642792417906131497","asset_bundle_scene_id":"1723942088082456989","avatar_id":""},{"game_engine":"unity","game_engine_version":20194,"platform":"pc","url":"https://cdn-content-ingress.altvr.com/environments/db/98/db98934539d6832b2d3dc658a5befb21-template-pc","description":null,"color_space":null,"aasm_state":"active","created_at":"2021-04-26T06:06:18.992-07:00","updated_at":"2021-04-26T06:06:18.992-07:00","layout":null,"crc":"3349876751","client_cache_key":"db98934539d6832b2d3dc658a5befb21","name":"template","stereo_render_mode":null,"uncompressed":null,"asset_bundle_id":"1723987459043230409","user_id":"1642792417906131497","asset_bundle_scene_id":"1723942088082456989","avatar_id":""}]}],"image_large":"https://cdn-content-ingress.altvr.com/uploads/space_template/image/1723942087688192410/99816fcbf5783cffc262745e7668363e.jpg","image_medium":"https://cdn-content-ingress.altvr.com/uploads/space_template/image/1723942087688192410/tile_99816fcbf5783cffc262745e7668363e.jpg","image_small":"https://cdn-content-ingress.altvr.com/uploads/space_template/image/1723942087688192410/tile_99816fcbf5783cffc262745e7668363e.jpg","image_thumbnail":"https://cdn-content-ingress.altvr.com/uploads/space_template/image/1723942087688192410/thumbnail_99816fcbf5783cffc262745e7668363e.jpg","banner_image_large":"https://cdn-content-ingress.altvr.com/defaults/default-1920x576.jpg","banner_image_medium":"https://cdn-content-ingress.altvr.com/defaults/default-1920x576.jpg","banner_image_small":"https://cdn-content-ingress.altvr.com/defaults/default-1920x576.jpg","name":"The Cyber Outpost"},{"space_template_sid":"the-stage-room-9777","selectable_by_non_admins":false,"graph_organization_id":null,"activity_name":"The Stage Room","selectable_for_experiences":false,"description":"In development. AussieGuy92.com for more.","desktop_capacity":null,"mobile_capacity":null,"disabled_for_public_activities":false,"admin":false,"created_at":"2021-04-27T06:48:42.758-07:00","updated_at":"2021-04-27T09:21:12.430-07:00","tutorial":null,"is_featured":null,"space_template_id":"1724733573715461050","recording_id":"","asset_bundle_scenes":[{"aasm_state":"active","name":"Autogenerated for SpaceTemplate 1724733573715461050","created_at":"2021-04-27T06:48:42.816-07:00","updated_at":"2021-04-27T09:21:12.428-07:00","asset_bundle_scene_id":"1724733573975507901","user_id":"1642792417906131497","asset_bundles":[{"game_engine":"unity","game_engine_version":20194,"platform":"android","url":"https://cdn-content-ingress.altvr.com/environments/fa/52/fa521f646cb2688d89a436bc9ce539aa-template-android","description":null,"color_space":null,"aasm_state":"active","created_at":"2021-04-27T09:21:12.355-07:00","updated_at":"2021-04-27T09:21:12.355-07:00","layout":null,"crc":"3355314988","client_cache_key":"fa521f646cb2688d89a436bc9ce539aa","name":"template","stereo_render_mode":null,"uncompressed":null,"asset_bundle_id":"1724810325879948275","user_id":"1642792417906131497","asset_bundle_scene_id":"1724733573975507901","avatar_id":""},{"game_engine":"unity","game_engine_version":20194,"platform":"pc","url":"https://cdn-content-ingress.altvr.com/environments/fa/52/fa521f646cb2688d89a436bc9ce539aa-template-pc","description":null,"color_space":null,"aasm_state":"active","created_at":"2021-04-27T09:21:11.652-07:00","updated_at":"2021-04-27T09:21:11.652-07:00","layout":null,"crc":"1743325715","client_cache_key":"fa521f646cb2688d89a436bc9ce539aa","name":"template","stereo_render_mode":null,"uncompressed":null,"asset_bundle_id":"1724810319982756849","user_id":"1642792417906131497","asset_bundle_scene_id":"1724733573975507901","avatar_id":""}]}],"image_large":"https://cdn-content-ingress.altvr.com/uploads/space_template/image/1724733573715461050/c1d9dc5a7cb1dd3538344c7b620e46b1.jpg","image_medium":"https://cdn-content-ingress.altvr.com/uploads/space_template/image/1724733573715461050/tile_c1d9dc5a7cb1dd3538344c7b620e46b1.jpg","image_small":"https://cdn-content-ingress.altvr.com/uploads/space_template/image/1724733573715461050/tile_c1d9dc5a7cb1dd3538344c7b620e46b1.jpg","image_thumbnail":"https://cdn-content-ingress.altvr.com/uploads/space_template/image/1724733573715461050/thumbnail_c1d9dc5a7cb1dd3538344c7b620e46b1.jpg","banner_image_large":"https://cdn-content-ingress.altvr.com/defaults/default-1920x576.jpg","banner_image_medium":"https://cdn-content-ingress.altvr.com/defaults/default-1920x576.jpg","banner_image_small":"https://cdn-content-ingress.altvr.com/defaults/default-1920x576.jpg","name":"The Stage Room"},{"space_template_sid":"tutorial--7090","selectable_by_non_admins":false,"graph_organization_id":null,"activity_name":"Tutorial ","selectable_for_experiences":false,"description":"for testing new unity version","desktop_capacity":null,"mobile_capacity":null,"disabled_for_public_activities":false,"admin":false,"created_at":"2021-04-21T13:41:42.802-07:00","updated_at":"2021-04-26T10:08:34.211-07:00","tutorial":null,"is_featured":null,"space_template_id":"1720592789353267595","recording_id":"","asset_bundle_scenes":[{"aasm_state":"active","name":"Autogenerated for SpaceTemplate 1720592789353267595","created_at":"2021-04-21T13:41:42.887-07:00","updated_at":"2021-04-26T10:08:34.208-07:00","asset_bundle_scene_id":"1720592789873361294","user_id":"1610370333934617056","asset_bundles":[{"game_engine":"unity","game_engine_version":20194,"platform":"android","url":"https://cdn-content-ingress.altvr.com/environments/7a/ed/7aed6c37999477cd1e34b744551bb0c1-template-android","description":null,"color_space":null,"aasm_state":"active","created_at":"2021-04-26T10:08:34.087-07:00","updated_at":"2021-04-26T10:08:34.087-07:00","layout":null,"crc":"2017365955","client_cache_key":"7aed6c37999477cd1e34b744551bb0c1","name":"template","stereo_render_mode":null,"uncompressed":null,"asset_bundle_id":"1724109388307759461","user_id":"1610370333934617056","asset_bundle_scene_id":"1720592789873361294","avatar_id":""},{"game_engine":"unity","game_engine_version":20194,"platform":"pc","url":"https://cdn-content-ingress.altvr.com/environments/7a/ed/7aed6c37999477cd1e34b744551bb0c1-template-pc","description":null,"color_space":null,"aasm_state":"active","created_at":"2021-04-26T10:08:33.928-07:00","updated_at":"2021-04-26T10:08:33.928-07:00","layout":null,"crc":"2512598328","client_cache_key":"7aed6c37999477cd1e34b744551bb0c1","name":"template","stereo_render_mode":null,"uncompressed":null,"asset_bundle_id":"1724109386990748003","user_id":"1610370333934617056","asset_bundle_scene_id":"1720592789873361294","avatar_id":""}]}],"image_large":"https://cdn-content-ingress.altvr.com/defaults/default-560x315.jpg","image_medium":"https://cdn-content-ingress.altvr.com/defaults/default-560x315.jpg","image_small":"https://cdn-content-ingress.altvr.com/defaults/default-560x315.jpg","image_thumbnail":"https://cdn-content-ingress.altvr.com/defaults/default-560x315.jpg","banner_image_large":"https://cdn-content-ingress.altvr.com/defaults/default-1920x576.jpg","banner_image_medium":"https://cdn-content-ingress.altvr.com/defaults/default-1920x576.jpg","banner_image_small":"https://cdn-content-ingress.altvr.com/defaults/default-1920x576.jpg","name":"Tutorial "},{"space_template_sid":"wendi-kent-colab-4810","selectable_by_non_admins":false,"graph_organization_id":null,"activity_name":"Wendi Kent Colab","selectable_for_experiences":false,"description":"","desktop_capacity":null,"mobile_capacity":null,"disabled_for_public_activities":false,"admin":false,"created_at":"2021-05-13T11:19:05.158-07:00","updated_at":"2021-05-13T11:43:07.329-07:00","tutorial":null,"is_featured":null,"space_template_id":"1736466068743913614","recording_id":"","asset_bundle_scenes":[{"aasm_state":"active","name":"Autogenerated for SpaceTemplate 1736466068743913614","created_at":"2021-05-13T11:19:05.218-07:00","updated_at":"2021-05-13T11:43:07.327-07:00","asset_bundle_scene_id":"1736466069003960465","user_id":"1610370333934617056","asset_bundles":[{"game_engine":"unity","game_engine_version":20194,"platform":"android","url":"https://cdn-content-ingress.altvr.com/environments/4e/1e/4e1e4555e9cb411150eaedefd3a4f0e7-template-android","description":null,"color_space":null,"aasm_state":"active","created_at":"2021-05-13T11:43:07.282-07:00","updated_at":"2021-05-13T11:43:07.282-07:00","layout":null,"crc":"389773476","client_cache_key":"4e1e4555e9cb411150eaedefd3a4f0e7","name":"template","stereo_render_mode":null,"uncompressed":null,"asset_bundle_id":"1736478165955511282","user_id":"1610370333934617056","asset_bundle_scene_id":"1736466069003960465","avatar_id":""},{"game_engine":"unity","game_engine_version":20194,"platform":"pc","url":"https://cdn-content-ingress.altvr.com/environments/4e/1e/4e1e4555e9cb411150eaedefd3a4f0e7-template-pc","description":null,"color_space":null,"aasm_state":"active","created_at":"2021-05-13T11:43:07.135-07:00","updated_at":"2021-05-13T11:43:07.135-07:00","layout":null,"crc":"2890401584","client_cache_key":"4e1e4555e9cb411150eaedefd3a4f0e7","name":"template","stereo_render_mode":null,"uncompressed":null,"asset_bundle_id":"1736478164646888432","user_id":"1610370333934617056","asset_bundle_scene_id":"1736466069003960465","avatar_id":""}]}],"image_large":"https://cdn-content-ingress.altvr.com/defaults/default-560x315.jpg","image_medium":"https://cdn-content-ingress.altvr.com/defaults/default-560x315.jpg","image_small":"https://cdn-content-ingress.altvr.com/defaults/default-560x315.jpg","image_thumbnail":"https://cdn-content-ingress.altvr.com/defaults/default-560x315.jpg","banner_image_large":"https://cdn-content-ingress.altvr.com/defaults/default-1920x576.jpg","banner_image_medium":"https://cdn-content-ingress.altvr.com/defaults/default-1920x576.jpg","banner_image_small":"https://cdn-content-ingress.altvr.com/defaults/default-1920x576.jpg","name":"Wendi Kent Colab"}],"pagination":{"page":1,"pages":1,"count":8}}